test_10_13_2023/__init__.py
test_10_13_2023-0.0.1.dist-info/METADATA
test_10_13_2023-0.0.1.dist-info/WHEEL
test_10_13_2023-0.0.1.dist-info/top_level.txt
test_10_13_2023-0.0.1.dist-info/RECORD
