Metadata-Version: 2.1
Name: test-10-13-2023
Version: 0.0.1
Summary: x
Author: x
